pretix_payment_fees/__init__.py
pretix_payment_fees/admin_views.py
pretix_payment_fees/apps.py
pretix_payment_fees/forms.py
pretix_payment_fees/models.py
pretix_payment_fees/oauth_views.py
pretix_payment_fees/signals.py
pretix_payment_fees/urls.py
pretix_payment_fees/views.py
pretix_payment_fees/exporters/__init__.py
pretix_payment_fees/exporters/accounting_report_psp.py
pretix_payment_fees/exporters/payment_list_psp.py
pretix_payment_fees/locale/django.pot
pretix_payment_fees/locale/de/LC_MESSAGES/django.mo
pretix_payment_fees/locale/de/LC_MESSAGES/django.po
pretix_payment_fees/locale/en/LC_MESSAGES/django.mo
pretix_payment_fees/locale/en/LC_MESSAGES/django.po
pretix_payment_fees/locale/es/LC_MESSAGES/django.mo
pretix_payment_fees/locale/es/LC_MESSAGES/django.po
pretix_payment_fees/locale/fr/LC_MESSAGES/django.mo
pretix_payment_fees/locale/fr/LC_MESSAGES/django.po
pretix_payment_fees/locale/it/LC_MESSAGES/django.mo
pretix_payment_fees/locale/it/LC_MESSAGES/django.po
pretix_payment_fees/locale/nl/LC_MESSAGES/django.mo
pretix_payment_fees/locale/nl/LC_MESSAGES/django.po
pretix_payment_fees/locale/pl/LC_MESSAGES/django.mo
pretix_payment_fees/locale/pl/LC_MESSAGES/django.po
pretix_payment_fees/locale/pt/LC_MESSAGES/django.mo
pretix_payment_fees/locale/pt/LC_MESSAGES/django.po
pretix_payment_fees/management/__init__.py
pretix_payment_fees/management/commands/__init__.py
pretix_payment_fees/management/commands/sync_psp_fees.py
pretix_payment_fees/migrations/0001_initial.py
pretix_payment_fees/migrations/0002_add_mollie_oauth_fields.py
pretix_payment_fees/migrations/0003_settlement_rate_cache.py
pretix_payment_fees/migrations/0004_add_auto_sync_fields.py
pretix_payment_fees/migrations/__init__.py
pretix_payment_fees/psp/__init__.py
pretix_payment_fees/psp/mollie_client.py
pretix_payment_fees/psp/mollie_oauth_client.py
pretix_payment_fees/psp/sumup_client.py
pretix_payment_fees/renderers/__init__.py
pretix_payment_fees/renderers/accounting_pdf_renderer.py
pretix_payment_fees-1.0.0.dist-info/licenses/LICENSE
pretix_payment_fees-1.0.0.dist-info/METADATA
pretix_payment_fees-1.0.0.dist-info/WHEEL
pretix_payment_fees-1.0.0.dist-info/entry_points.txt
pretix_payment_fees-1.0.0.dist-info/top_level.txt
pretix_payment_fees-1.0.0.dist-info/RECORD
