Metadata-Version: 2.4
Name: pretix-payment-fees
Version: 1.0.0
Summary: Pretix plugin for tracking and reporting payment provider fees (Mollie, SumUp)
Author-email: Valentin Gosselin <valentin@gosselin.pro>
License: Apache-2.0
Project-URL: Homepage, https://github.com/valentin-gosselin/pretix-payment-fees
Project-URL: Documentation, https://github.com/valentin-gosselin/pretix-payment-fees#readme
Project-URL: Repository, https://github.com/valentin-gosselin/pretix-payment-fees.git
Project-URL: Issues, https://github.com/valentin-gosselin/pretix-payment-fees/issues
Project-URL: Changelog, https://github.com/valentin-gosselin/pretix-payment-fees/blob/main/CHANGELOG.md
Keywords: pretix,plugin,payment,fees,mollie,sumup,psp,accounting,export
Classifier: Development Status :: 4 - Beta
Classifier: Framework :: Django
Classifier: Framework :: Django :: 3.2
Classifier: Framework :: Django :: 4.0
Classifier: Framework :: Django :: 4.1
Classifier: Framework :: Django :: 4.2
Classifier: Intended Audience :: Developers
Classifier: Intended Audience :: Other Audience
Classifier: License :: OSI Approved :: Apache Software License
Classifier: Programming Language :: Python :: 3
Classifier: Programming Language :: Python :: 3.11
Classifier: Programming Language :: Python :: 3.12
Classifier: Topic :: Internet :: WWW/HTTP :: Dynamic Content
Classifier: Topic :: Office/Business :: Financial :: Accounting
Classifier: Environment :: Plugins
Classifier: Natural Language :: English
Classifier: Natural Language :: French
Classifier: Natural Language :: German
Classifier: Natural Language :: Spanish
Classifier: Natural Language :: Dutch
Classifier: Natural Language :: Italian
Classifier: Natural Language :: Portuguese
Classifier: Natural Language :: Polish
Requires-Python: >=3.11
License-File: LICENSE
Requires-Dist: weasyprint>=62.0
Requires-Dist: openpyxl>=3.1.0
Requires-Dist: requests>=2.28.0
Provides-Extra: dev
Requires-Dist: black>=23.0.0; extra == "dev"
Requires-Dist: isort>=5.12.0; extra == "dev"
Dynamic: license-file
